{
  "$schema": "https://raw.githubusercontent.com/googleapis/release-please/main/schemas/config.json",
  "include-v-in-tag": true,
  "tag-separator": "@",
  "separate-pull-requests": true,
  "group-pull-request-title-pattern": "chore: release ${component}",
  "draft": false,
  "prerelease": true,
  "prerelease-type": "beta",
  "release-type": "node",
  "packages": {
    ".": {
      "component": "solstatus"
    },
    "packages/app": {
      "component": "@solstatus/app"
    },
    "packages/api": {
      "component": "@solstatus/api"
    },
    "packages/infra": {
      "component": "@solstatus/infra"
    },
    "packages/common": {
      "component": "@solstatus/common"
    }
  },
  "plugins": [
    {
      "type": "node-workspace",
      "updatePeerDependencies": true
    }
  ],
  "extra-files": ["packages/app/next.config.ts"]
}
